README.rst
setup.py
bin/nft
nft/__init__.py
nft/nft.py
nft.egg-info/PKG-INFO
nft.egg-info/SOURCES.txt
nft.egg-info/dependency_links.txt
nft.egg-info/not-zip-safe
nft.egg-info/requires.txt
nft.egg-info/top_level.txt
nft/templates/C.c
nft/templates/Java.java
nft/templates/README.md
nft/templates/README.rst
nft/templates/README.txt
nft/templates/__init__.py
nft/templates/bash.sh
nft/templates/csh.csh
nft/templates/header.h
nft/templates/python.py
nft/templates/ruby.rb