Metadata-Version: 1.1
Name: nft
Version: 2.6
Summary: A tool for quickly creating a New File form a Template
Home-page: https://github.com/dan-rds/NFT
Author: Daniel Richards
Author-email: ddrichar@ucsc.edu
License: Expat License
Keywords: automation,template
Platform: UNKNOWN
Classifier: Programming Language :: Python :: 3
